_fork_locking.so
native_fork_locking-0.2.2.dist-info/METADATA
native_fork_locking-0.2.2.dist-info/WHEEL
native_fork_locking-0.2.2.dist-info/top_level.txt
native_fork_locking-0.2.2.dist-info/RECORD
